torchts/__init__.py
torchts/nn/__init__.py
torchts/nn/graph.py
torchts/nn/loss.py
torchts/nn/model.py
torchts/nn/models/__init__.py
torchts/nn/models/dcrnn.py
torchts/nn/models/seq2seq.py
torchts/utils/__init__.py
torchts/utils/data.py
torchts/utils/graph.py
torchts-0.1.1.dist-info/LICENSE
torchts-0.1.1.dist-info/WHEEL
torchts-0.1.1.dist-info/METADATA
torchts-0.1.1.dist-info/RECORD
