Metadata-Version: 2.1
Name: torchts
Version: 0.1.1
Summary: Time series forecasting with PyTorch
Home-page: https://rose-stl-lab.github.io/torchTS
License: MIT
Keywords: deep-learning,machine-learning,time-series,pytorch
Author: TorchTS Team
Author-email: torchts@googlegroups.com
Requires-Python: >=3.7,<3.10
Classifier: Development Status :: 3 - Alpha
Classifier: Intended Audience :: Developers
Classifier: Intended Audience :: Science/Research
Classifier: License :: OSI Approved :: MIT License
Classifier: Programming Language :: Python :: 3
Classifier: Programming Language :: Python :: 3.7
Classifier: Programming Language :: Python :: 3.8
Classifier: Programming Language :: Python :: 3.9
Classifier: Topic :: Scientific/Engineering
Classifier: Topic :: Software Development :: Libraries :: Python Modules
Requires-Dist: pytorch-lightning (>=1.2,<2.0)
Requires-Dist: scipy (>=1.7.1,<2.0.0)
Requires-Dist: torch (>=1.4,<2.0)
Project-URL: Documentation, https://rose-stl-lab.github.io/torchTS/docs
Project-URL: Repository, https://github.com/Rose-STL-Lab/torchTS
